fiter/__init__.py
fiter/number.py
fiter/utils.py
fiter-1.0.0.dist-info/METADATA
fiter-1.0.0.dist-info/WHEEL
fiter-1.0.0.dist-info/top_level.txt
fiter-1.0.0.dist-info/RECORD
